tgm.py
tgm-0.0.3.dist-info/LICENSE
tgm-0.0.3.dist-info/METADATA
tgm-0.0.3.dist-info/WHEEL
tgm-0.0.3.dist-info/top_level.txt
tgm-0.0.3.dist-info/RECORD
