Metadata-Version: 2.1
Name: tgm
Version: 0.0.3
Summary: Python code to identify temporal K_{2,h} motifs in networks
Home-page: https://github.com/ftheberge/tgm
Author: François Théberge
Author-email: theberge@ieee.org
License: MIT
Platform: UNKNOWN
Classifier: Development Status :: 4 - Beta
Classifier: License :: OSI Approved :: MIT License
Classifier: Programming Language :: Python
Classifier: Programming Language :: Python :: 3
Classifier: Topic :: Scientific/Engineering
Classifier: Topic :: Software Development :: Libraries :: Python Modules
Classifier: Intended Audience :: Science/Research
Requires-Python: >=3.7
License-File: LICENSE
Requires-Dist: numpy
Requires-Dist: pandas
Requires-Dist: igraph
